stds/__init__.py
stds-0.1.3.dist-info/WHEEL
stds-0.1.3.dist-info/METADATA
stds-0.1.3.dist-info/RECORD
